langchain_agb_integration/__init__.py
langchain_agb_integration/py.typed
langchain_agb_integration/toolkits.py
langchain_agb_integration/tools.py
langchain_agb_integration-0.1.1.dist-info/METADATA
langchain_agb_integration-0.1.1.dist-info/WHEEL
langchain_agb_integration-0.1.1.dist-info/licenses/LICENSE
langchain_agb_integration-0.1.1.dist-info/RECORD
